django_postgres_readonly/__init__.py
django_postgres_readonly/base.py
django_postgres_readonly-1.0.0.dist-info/DESCRIPTION.rst
django_postgres_readonly-1.0.0.dist-info/METADATA
django_postgres_readonly-1.0.0.dist-info/RECORD
django_postgres_readonly-1.0.0.dist-info/WHEEL
django_postgres_readonly-1.0.0.dist-info/metadata.json
django_postgres_readonly-1.0.0.dist-info/top_level.txt
