Metadata-Version: 2.0
Name: django-postgres-readonly
Version: 1.0.0
Summary: A backend for Django and Postgres that sets up a readonly connection
Home-page: https://github.com/opbeat/django-postgres-readonly
Author: Opbeat
Author-email: benjamin@opbeat.com
License: BSD
Keywords: django postgres
Platform: UNKNOWN
Classifier: Development Status :: 5 - Production/Stable
Classifier: License :: OSI Approved :: BSD License
Classifier: Framework :: Django
Classifier: Programming Language :: Python :: 2
Classifier: Programming Language :: Python :: 2.7
Classifier: Programming Language :: Python :: 3
Classifier: Programming Language :: Python :: 3.3
Classifier: Programming Language :: Python :: 3.4
Classifier: Programming Language :: Python :: 3.5
Requires-Dist: Django
Requires-Dist: psycopg2
Provides-Extra: test
Requires-Dist: coverage; extra == 'test'
